nhentei/__init__.py
nhentei/nfunctions.py
nhentei-2.0.dist-info/LICENSE
nhentei-2.0.dist-info/METADATA
nhentei-2.0.dist-info/WHEEL
nhentei-2.0.dist-info/top_level.txt
nhentei-2.0.dist-info/RECORD
