Metadata-Version: 2.1
Name: nhentei
Version: 2.0
Summary: nHentai API implementation
Home-page: https://github.com/sa-koitchio/nhentei
Author: Sa_Ko
Author-email: alphaschleimcmds@gmail.com
License: UNKNOWN
Project-URL: Bug Tracker, https://github.com/sa-koitchio/nhentei
Platform: UNKNOWN
Classifier: Programming Language :: Python :: 3
Classifier: License :: OSI Approved :: MIT License
Classifier: Operating System :: OS Independent
Requires-Python: >=3.6
